<?xml version="1.0" encoding="UTF-8"?>
<!DOCTYPE mapper PUBLIC "-//mybatis.org//DTD Mapper 3.0//EN" "http://mybatis.org/dtd/mybatis-3-mapper.dtd">
<mapper namespace="com.yadda.integrate.provider.dao.AppUserTempMapper">
  <resultMap id="BaseResultMap" type="com.yadda.integrate.model.AppUserTemp">
    <!--
      WARNING - @mbg.generated
      This element is automatically generated by MyBatis Generator, do not modify.
      This element was generated on Tue Oct 11 12:42:32 CST 2016.
    -->
    <id column="FId" jdbcType="INTEGER" property="fid" />
    <result column="FNumber" jdbcType="VARCHAR" property="fnumber" />
    <result column="FCreateTime" jdbcType="TIMESTAMP" property="fcreatetime" />
    <result column="FScene" jdbcType="VARCHAR" property="fscene" />
  </resultMap>
  <sql id="Base_Column_List">
    <!--
      WARNING - @mbg.generated
      This element is automatically generated by MyBatis Generator, do not modify.
      This element was generated on Tue Oct 11 12:42:32 CST 2016.
    -->
    FId, FNumber, FCreateTime, FScene
  </sql>
  <select id="selectByPrimaryKey" parameterType="java.lang.Integer" resultMap="BaseResultMap">
    <!--
      WARNING - @mbg.generated
      This element is automatically generated by MyBatis Generator, do not modify.
      This element was generated on Tue Oct 11 12:42:32 CST 2016.
    -->
    select 
    <include refid="Base_Column_List" />
    from t_AppUserTemp
    where FId = #{fid,jdbcType=INTEGER}
  </select>
  <delete id="deleteByPrimaryKey" parameterType="java.lang.Integer">
    <!--
      WARNING - @mbg.generated
      This element is automatically generated by MyBatis Generator, do not modify.
      This element was generated on Tue Oct 11 12:42:32 CST 2016.
    -->
    delete from t_AppUserTemp
    where FId = #{fid,jdbcType=INTEGER}
  </delete>
  <insert id="insert" parameterType="com.yadda.integrate.model.AppUserTemp">
    <!--
      WARNING - @mbg.generated
      This element is automatically generated by MyBatis Generator, do not modify.
      This element was generated on Tue Oct 11 12:42:32 CST 2016.
    -->
    insert into t_AppUserTemp (FId, FNumber, FCreateTime, 
      FScene)
    values (#{fid,jdbcType=INTEGER}, #{fnumber,jdbcType=VARCHAR}, #{fcreatetime,jdbcType=TIMESTAMP}, 
      #{fscene,jdbcType=VARCHAR})
  </insert>
  <insert id="insertSelective" parameterType="com.yadda.integrate.model.AppUserTemp">
    <!--
      WARNING - @mbg.generated
      This element is automatically generated by MyBatis Generator, do not modify.
      This element was generated on Tue Oct 11 12:42:32 CST 2016.
    -->
    insert into t_AppUserTemp
    <trim prefix="(" suffix=")" suffixOverrides=",">
      <if test="fid != null">
        FId,
      </if>
      <if test="fnumber != null">
        FNumber,
      </if>
      <if test="fcreatetime != null">
        FCreateTime,
      </if>
      <if test="fscene != null">
        FScene,
      </if>
    </trim>
    <trim prefix="values (" suffix=")" suffixOverrides=",">
      <if test="fid != null">
        #{fid,jdbcType=INTEGER},
      </if>
      <if test="fnumber != null">
        #{fnumber,jdbcType=VARCHAR},
      </if>
      <if test="fcreatetime != null">
        #{fcreatetime,jdbcType=TIMESTAMP},
      </if>
      <if test="fscene != null">
        #{fscene,jdbcType=VARCHAR},
      </if>
    </trim>
  </insert>
  <update id="updateByPrimaryKeySelective" parameterType="com.yadda.integrate.model.AppUserTemp">
    <!--
      WARNING - @mbg.generated
      This element is automatically generated by MyBatis Generator, do not modify.
      This element was generated on Tue Oct 11 12:42:32 CST 2016.
    -->
    update t_AppUserTemp
    <set>
      <if test="fnumber != null">
        FNumber = #{fnumber,jdbcType=VARCHAR},
      </if>
      <if test="fcreatetime != null">
        FCreateTime = #{fcreatetime,jdbcType=TIMESTAMP},
      </if>
      <if test="fscene != null">
        FScene = #{fscene,jdbcType=VARCHAR},
      </if>
    </set>
    where FId = #{fid,jdbcType=INTEGER}
  </update>
  <update id="updateByPrimaryKey" parameterType="com.yadda.integrate.model.AppUserTemp">
    <!--
      WARNING - @mbg.generated
      This element is automatically generated by MyBatis Generator, do not modify.
      This element was generated on Tue Oct 11 12:42:32 CST 2016.
    -->
    update t_AppUserTemp
    set FNumber = #{fnumber,jdbcType=VARCHAR},
      FCreateTime = #{fcreatetime,jdbcType=TIMESTAMP},
      FScene = #{fscene,jdbcType=VARCHAR}
    where FId = #{fid,jdbcType=INTEGER}
  </update>
</mapper>